skywalker/__init__.py
skywalker/skywalker.py
skywalker/test.py
skywalker-0.0.22.dist-info/licenses/LICENSE
skywalker-0.0.22.dist-info/METADATA
skywalker-0.0.22.dist-info/WHEEL
skywalker-0.0.22.dist-info/top_level.txt
skywalker-0.0.22.dist-info/RECORD
