Metadata-Version: 2.4
Name: skywalker
Version: 0.0.22
Summary: Things I like in python
Home-page: https://github.com/dgerosa/skywalker
Author: Davide Gerosa
Author-email: davide.gerosa@unimib.it
License: MIT
License-File: LICENSE
Requires-Dist: matplotlib
Requires-Dist: tqdm
Requires-Dist: ediblepickle
Requires-Dist: deepdish
Requires-Dist: contexttimer
Requires-Dist: singleton_decorator
Dynamic: author
Dynamic: author-email
Dynamic: description
Dynamic: home-page
Dynamic: license
Dynamic: license-file
Dynamic: requires-dist
Dynamic: summary
